Metadata-Version: 1.1
Name: rrcache
Version: 0.0.1
Summary: just a practice
Home-page: UNKNOWN
Author: Turtle
Author-email: satyam.krait@gmail.com
License: MIT
Keywords: practice
Platform: UNKNOWN
Classifier: Development Status :: 5 - Production/Stable
Classifier: Intended Audience :: Education
Classifier: Operating System :: Microsoft :: Windows :: Windows 10
Classifier: License :: OSI Approved :: MIT License
Classifier: Programming Language :: Python :: 3
